ejbca_client/__init__.py
ejbca_client/client.py
ejbca_client/data.py
ejbca_client/exception.py
ejbca_client/utils.py
ejbca_client-1.2.0.dist-info/LICENSE
ejbca_client-1.2.0.dist-info/METADATA
ejbca_client-1.2.0.dist-info/WHEEL
ejbca_client-1.2.0.dist-info/top_level.txt
ejbca_client-1.2.0.dist-info/RECORD
